README.md
setup.py
pystdutils/__init__.py
pystdutils/assert_uitls.py
pystdutils/compat_utils.py
pystdutils/python_utils.py
pystdutils/url_utils.py
pystdutils.egg-info/PKG-INFO
pystdutils.egg-info/SOURCES.txt
pystdutils.egg-info/dependency_links.txt
pystdutils.egg-info/top_level.txt
tests/__init__.py
tests/test_assert_utils.py
tests/test_python_utils.py