Metadata-Version: 1.1
Name: pystdutils
Version: 0.1
Summary: Python Utils for Python2 and Python3
Home-page: https://github.com/hezhiming/pystduitls
Author: he.zhiming
Author-email: he.zhiming@foxmail.com
License: MIT
Keywords: Python Utils
Platform: any
Classifier: Development Status :: 5 - Production/Stable
Classifier: Intended Audience :: Developers
Classifier: License :: OSI Approved :: MIT License
Classifier: Operating System :: OS Independent
Classifier: Programming Language :: Python :: 3.6
Classifier: Topic :: Software Development :: Libraries
Classifier: Topic :: Utilities
